glow/__init__.py
glow/__main__.py
glow/glow/__init__.py
glow/glow/helpers.py
glow/glow/integrations.py
glow/glow/messages.py
glow/glow/models.py
glow/glow/validators.py
git_glow-0.2.12.dist-info/LICENSE
git_glow-0.2.12.dist-info/METADATA
git_glow-0.2.12.dist-info/WHEEL
git_glow-0.2.12.dist-info/entry_points.txt
git_glow-0.2.12.dist-info/top_level.txt
git_glow-0.2.12.dist-info/RECORD
