Metadata-Version: 2.1
Name: git-glow
Version: 0.2.12
Summary: A new git extension to use git flow branching model automatically with Jira and Github
Home-page: https://github.com/nicolasramy/git-glow
Author: Nicolas RAMY
Author-email: nicolas.ramy@darkelda.com
License: MIT
Classifier: Development Status :: 4 - Beta
Classifier: License :: OSI Approved :: MIT License
Classifier: Operating System :: OS Independent
Classifier: Programming Language :: Python :: 3.7
Classifier: Topic :: Terminals
Classifier: Topic :: Utilities
License-File: LICENSE
Requires-Dist: colorama ==0.4.4
Requires-Dist: click ==8.1.3
Requires-Dist: emoji ==1.2.0
Requires-Dist: gitpython ==3.1.37
Requires-Dist: idna ==2.10
Requires-Dist: python-slugify ==4.0.1
Requires-Dist: requests ==2.31.0
Requires-Dist: semver ==2.13.0
Requires-Dist: termcolor ==1.1.0
Requires-Dist: urllib3[secure] ==1.26.18
